boilr/__init__.py
boilr/_version.py
boilr/data.py
boilr/eval.py
boilr/experiments.py
boilr/models.py
boilr/options.py
boilr/trainer.py
boilr/nn/__init__.py
boilr/nn/init.py
boilr/nn/modules.py
boilr/nn/utils.py
boilr/utils/__init__.py
boilr/utils/meta.py
boilr/utils/summarize.py
boilr/utils/utils.py
boilr/utils/viz.py
boilr-0.7.4.dist-info/LICENSE
boilr-0.7.4.dist-info/METADATA
boilr-0.7.4.dist-info/WHEEL
boilr-0.7.4.dist-info/top_level.txt
boilr-0.7.4.dist-info/RECORD
