Metadata-Version: 2.1
Name: boilr
Version: 0.7.4
Summary: Basic framework for training models with PyTorch
Home-page: https://github.com/addtt/boiler-pytorch
Author: Andrea Dittadi
Author-email: andrea.dittadi@gmail.com
License: UNKNOWN
Platform: UNKNOWN
Classifier: Programming Language :: Python :: 3
Classifier: License :: OSI Approved :: MIT License
Classifier: Operating System :: OS Independent
Requires-Python: >=3.6
Requires-Dist: numpy (>=1.18)
Requires-Dist: torch (>=1.4)
Requires-Dist: torchvision (>=0.5)
Requires-Dist: matplotlib (>=3.2)
Requires-Dist: tqdm
Requires-Dist: pillow (>=7.1)
